Workbook

Sheet Monthly
A1: Month | B1: Nifty expiry (7 lots) ₹ | C1: Sensex expiry (7 lots) ₹ | D1: Weekend (5 lots) ₹ | E1: Total ₹ | F1: % of ₹7.5 L | G1: Cumulative ₹ | I1: Capital ₹ | J1: 750000
A2: Oct 2016 | B2: -7788 | C2: 0 | D2: 0 | E2: =B2+C2+D2 -> -7788 | F2: =E2/$J$1 -> -0.010384 | G2: =E2 -> -7788
A3: Nov 2016 | B3: -6272 | C3: 0 | D3: -1786 | E3: =B3+C3+D3 -> -8058 | F3: =E3/$J$1 -> -0.010744 | G3: =G2+E3 -> -15846
A4: Dec 2016 | B4: 3001 | C4: 0 | D4: 6546 | E4: =B4+C4+D4 -> 9547 | F4: =E4/$J$1 -> 0.012729333 | G4: =G3+E4 -> -6299
A5: Jan 2017 | B5: -4028 | C5: 0 | D5: -2034 | E5: =B5+C5+D5 -> -6062 | F5: =E5/$J$1 -> -0.0080826667 | G5: =G4+E5 -> -12361
A6: Feb 2017 | B6: 3309 | C6: 0 | D6: 9716 | E6: =B6+C6+D6 -> 13025 | F6: =E6/$J$1 -> 0.017366667 | G6: =G5+E6 -> 664
A7: Mar 2017 | B7: -4013 | C7: 0 | D7: 11715 | E7: =B7+C7+D7 -> 7702 | F7: =E7/$J$1 -> 0.010269333 | G7: =G6+E7 -> 8366
A8: Apr 2017 | B8: -1457 | C8: 0 | D8: 0 | E8: =B8+C8+D8 -> -1457 | F8: =E8/$J$1 -> -0.0019426667 | G8: =G7+E8 -> 6909
A9: May 2017 | B9: 3000 | C9: 0 | D9: -3776 | E9: =B9+C9+D9 -> -776 | F9: =E9/$J$1 -> -0.0010346667 | G9: =G8+E9 -> 6133
A10: Jun 2017 | B10: -6896 | C10: 0 | D10: -464 | E10: =B10+C10+D10 -> -7360 | F10: =E10/$J$1 -> -0.0098133333 | G10: =G9+E10 -> -1227
A11: Jul 2017 | B11: -9312 | C11: 0 | D11: 8185 | E11: =B11+C11+D11 -> -1127 | F11: =E11/$J$1 -> -0.0015026667 | G11: =G10+E11 -> -2354
A12: Aug 2017 | B12: 53 | C12: 0 | D12: 1861 | E12: =B12+C12+D12 -> 1914 | F12: =E12/$J$1 -> 0.002552 | G12: =G11+E12 -> -440
A13: Sep 2017 | B13: -1977 | C13: 0 | D13: 14159 | E13: =B13+C13+D13 -> 12182 | F13: =E13/$J$1 -> 0.016242667 | G13: =G12+E13 -> 11742
A14: Oct 2017 | B14: 3545 | C14: 0 | D14: 12183 | E14: =B14+C14+D14 -> 15728 | F14: =E14/$J$1 -> 0.020970667 | G14: =G13+E14 -> 27470
... A122: Oct 2026 | B122: 23238 | C122: 27241 | D122: 0 | E122: =B122+C122+D122 -> 50479 | F122: =E122/$J$1 -> 0.067305333 | G122: =G121+E122 -> 5476338
A123: Total | B123: =SUM(B2:B122) -> 2072097 | C123: =SUM(C2:C122) -> 1225209 | D123: =SUM(D2:D122) -> 2179032 | E123: =SUM(E2:E122) -> 5476338
A125: Nifty expiry: 7 hedged lots (2/2/3 at 9:22/9:35/10:05), 40% SL/leg, other leg SL to cost, 1 re-entry only if day green, day stop -20k, DD>30k -> 3 lots, exit 15:15. Monthly expiries only until Feb 2019.
A126: Sensex expiry: same, 2/2/3 at 9:45/10:05/10:35, from 15 May 2023 (weekly Sensex options started then).
A127: Weekend: 5 lots Nifty futures + 1% OTM protective option, only if Friday direction agrees with 50 EMA AND 200 SMA, skip long weekends, Fri close -> Mon open (real NSE prices).
A128: After costs, before tax. Expiry trades use rebuilt minute prices (estimates). Oct 2016 = from 26 Oct; Oct 2026 = to ~23 Oct.

Sheet Yearly
A1: Year | B1: Nifty ₹ | C1: Sensex ₹ | D1: Weekend ₹ | E1: Total ₹ | F1: % of ₹7.5 L
A2: 2016 | B2: -11059 | C2: 0 | D2: 4761 | E2: =B2+C2+D2 -> -6298 | F2: =E2/Monthly!$J$1 -> -0.0083973333
A3: 2017 | B3: -26588 | C3: 0 | D3: 35286 | E3: =B3+C3+D3 -> 8698 | F3: =E3/Monthly!$J$1 -> 0.011597333
A4: 2018 | B4: -7279 | C4: 0 | D4: 10984 | E4: =B4+C4+D4 -> 3705 | F4: =E4/Monthly!$J$1 -> 0.00494
A5: 2019 | B5: 35562 | C5: 0 | D5: 145315 | E5: =B5+C5+D5 -> 180877 | F5: =E5/Monthly!$J$1 -> 0.24116933
A6: 2020 | B6: 143376 | C6: 0 | D6: 103391 | E6: =B6+C6+D6 -> 246767 | F6: =E6/Monthly!$J$1 -> 0.32902267
A7: 2021 | B7: 240705 | C7: 0 | D7: 169098 | E7: =B7+C7+D7 -> 409803 | F7: =E7/Monthly!$J$1 -> 0.546404
A8: 2022 | B8: 306881 | C8: 0 | D8: 319175 | E8: =B8+C8+D8 -> 626056 | F8: =E8/Monthly!$J$1 -> 0.83474133
A9: 2023 | B9: 61080 | C9: 147716 | D9: 115432 | E9: =B9+C9+D9 -> 324228 | F9: =E9/Monthly!$J$1 -> 0.432304
A10: 2024 | B10: 478685 | C10: 540352 | D10: 141483 | E10: =B10+C10+D10 -> 1160520 | F10: =E10/Monthly!$J$1 -> 1.54736
A11: 2025 | B11: 387076 | C11: 402415 | D11: 561865 | E11: =B11+C11+D11 -> 1351356 | F11: =E11/Monthly!$J$1 -> 1.801808
A12: 2026 | B12: 463656 | C12: 134728 | D12: 572242 | E12: =B12+C12+D12 -> 1170626 | F12: =E12/Monthly!$J$1 -> 1.5608347
