Workbook

Sheet Summary
A1: Nifty expiry-day ATM straddle — 3 lots, backtest Jan 2016 – Oct 2026
A3: Metric | B3: Set A (9:22 + 9:35 + 10:05) | C3: Set B (9:45 + 10:05 + 10:35)
A4: Total profit ₹ | B4: =SUM('Set A daily'!P2:P440) -> 1327936 | C4: =SUM('Set B daily'!P2:P440) -> 1454534
A5: Expiry days traded | B5: =COUNT('Set A daily'!P2:P440) -> 439 | C5: =COUNT('Set B daily'!P2:P440) -> 439
A6: Average ₹ per expiry day | B6: =AVERAGE('Set A daily'!P2:P440) -> 3024.9112 | C6: =AVERAGE('Set B daily'!P2:P440) -> 3313.2893
A7: Win % | B7: =COUNTIF('Set A daily'!P2:P440,">0")/COUNT('Set A daily'!P2:P440) -> 0.70615034 | C7: =COUNTIF('Set B daily'!P2:P440,">0")/COUNT('Set B daily'!P2:P440) -> 0.73120729
A8: Best day ₹ | B8: =MAX('Set A daily'!P2:P440) -> 45765 | C8: =MAX('Set B daily'!P2:P440) -> 38547
A9: Worst day ₹ | B9: =MIN('Set A daily'!P2:P440) -> -14841 | C9: =MIN('Set B daily'!P2:P440) -> -14240
A10: Max drawdown ₹ | B10: =MIN('Set A daily'!R2:R440) -> -19120 | C10: =MIN('Set B daily'!R2:R440) -> -26927
A11: Average ₹ per year (10.8 yrs) | B11: =SUM('Set A daily'!P2:P440)/10.8 -> 122957.04 | C11: =SUM('Set B daily'!P2:P440)/10.8 -> 134679.07
A13: Notes and assumptions
A14: Rules: Nifty weekly expiry day only; sell 1 lot ATM CE + 1 lot ATM PE at each entry time (3 straddles a day); 30% stop-loss on each leg checked every minute; everything still open is bought back at 15:15.
A15: ₹ figures use today's lot size (65 qty) for every year; costs included: STT 0.1% on sell premium, ~0.04% other charges per side, ₹40 brokerage per leg round trip, 0.5 pt slippage per side, +1% slippage on stop fills.
A16: Minute-level option prices are not published for past years: prices are rebuilt from the real Nifty 1-minute path with Black-Scholes, using each day's implied volatility solved from the actual 9:15 straddle price in the NSE bhavcopy. Treat ₹ amounts as estimates; the comparison between entry times is more reliable.
A17: VIX = previous day's India VIX close (known before the trade). 2026 data runs to 23 Oct 2026. Approx. margin for 3 naked straddles: ₹7–7.5 lakh.
A18: Monthly and Yearly sheets are formulas on the daily sheets. Use the filter on the daily sheets to sort or filter by date, day or VIX.

Sheet Set A daily
A1: Date | B1: Year | C1: Month | D1: Day | E1: Nifty open | F1: VIX (prev close) | G1: 09:22 premium (pts) | H1: 09:22 P&L ₹ | I1: 09:22 legs stopped | J1: 09:35 premium (pts) | K1: 09:35 P&L ₹ | L1: 09:35 legs stopped | M1: 10:05 premium (pts) | N1: 10:05 P&L ₹ | O1: 10:05 legs stopped | P1: Total P&L ₹ (3 lots) | Q1: Cumulative ₹ | R1: Drawdown ₹
A2: 42397 | B2: =YEAR(A2) -> 2016 | C2: =MONTH(A2) -> 1 | D2: Thursday | E2: 7426.5 | F2: 19.06 | G2: 36.2 | H2: -966 | I2: 2 | J2: 36.6 | K2: -645 | L2: 1 | M2: 36 | N2: -535 | O2: 1 | P2: =H2+K2+N2 -> -2146 | Q2: =P2 -> -2146 | R2: =Q2-MAX(0,MAX($Q$2:Q2)) -> -2146
A3: 42425 | B3: =YEAR(A3) -> 2016 | C3: =MONTH(A3) -> 2 | D3: Thursday | E3: 7029.8 | F3: 22.96 | G3: 54.7 | H3: 1606 | I3: 1 | J3: 52.5 | K3: -1298 | L3: 2 | M3: 51 | N3: -1268 | O3: 2 | P3: =H3+K3+N3 -> -960 | Q3: =Q2+P3 -> -3106 | R3: =Q3-MAX(0,MAX($Q$2:Q3)) -> -3106
A4: 42460 | B4: =YEAR(A4) -> 2016 | C4: =MONTH(A4) -> 3 | D4: Thursday | E4: 7727.6 | F4: 16.81 | G4: 36.1 | H4: -964 | I4: 2 | J4: 35.4 | K4: -950 | L4: 2 | M4: 36.7 | N4: 1296 | O4: 1 | P4: =H4+K4+N4 -> -618 | Q4: =Q3+P4 -> -3724 | R4: =Q4-MAX(0,MAX($Q$2:Q4)) -> -3724
A5: 42488 | B5: =YEAR(A5) -> 2016 | C5: =MONTH(A5) -> 4 | D5: Thursday | E5: 7967.4 | F5: 16.35 | G5: 40.9 | H5: 136 | I5: 1 | J5: 42.4 | K5: -1093 | L5: 2 | M5: 37.7 | N5: 274 | O5: 1 | P5: =H5+K5+N5 -> -683 | Q5: =Q4+P5 -> -4407 | R5: =Q5-MAX(0,MAX($Q$2:Q5)) -> -4407
A6: 42516 | B6: =YEAR(A6) -> 2016 | C6: =MONTH(A6) -> 5 | D6: Thursday | E6: 7974.4 | F6: 15.52 | G6: 43.7 | H6: 539 | I6: 1 | J6: 46.3 | K6: -131 | L6: 1 | M6: 46 | N6: -1165 | O6: 2 | P6: =H6+K6+N6 -> -757 | Q6: =Q5+P6 -> -5164 | R6: =Q6-MAX(0,MAX($Q$2:Q6)) -> -5164
A7: 42551 | B7: =YEAR(A7) -> 2016 | C7: =MONTH(A7) -> 6 | D7: Thursday | E7: 8262.3 | F7: 16.16 | G7: 56.1 | H7: 403 | I7: 1 | J7: 56.1 | K7: 192 | L7: 1 | M7: 55 | N7: -1350 | O7: 2 | P7: =H7+K7+N7 -> -755 | Q7: =Q6+P7 -> -5919 | R7: =Q7-MAX(0,MAX($Q$2:Q7)) -> -5919
A8: 42579 | B8: =YEAR(A8) -> 2016 | C8: =MONTH(A8) -> 7 | D8: Thursday | E8: 8636.8 | F8: 15.43 | G8: 46.5 | H8: 1558 | I8: 0 | J8: 45.7 | K8: 1505 | L8: 0 | M8: 44.4 | N8: 1421 | O8: 0 | P8: =H8+K8+N8 -> 4484 | Q8: =Q7+P8 -> -1435 | R8: =Q8-MAX(0,MAX($Q$2:Q8)) -> -1435
A9: 42607 | B9: =YEAR(A9) -> 2016 | C9: =MONTH(A9) -> 8 | D9: Thursday | E9: 8666.8 | F9: 13.49 | G9: 60.3 | H9: 2226 | I9: 1 | J9: 57.8 | K9: 1913 | L9: 1 | M9: 56.8 | N9: 2091 | O9: 1 | P9: =H9+K9+N9 -> 6230 | Q9: =Q8+P9 -> 4795 | R9: =Q9-MAX(0,MAX($Q$2:Q9)) -> 0
A10: 42642 | B10: =YEAR(A10) -> 2016 | C10: =MONTH(A10) -> 9 | D10: Thursday | E10: 8790.8 | F10: 13.85 | G10: 41.5 | H10: 491 | I10: 1 | J10: 41.5 | K10: 238 | L10: 1 | M10: 40.5 | N10: 61 | O10: 1 | P10: =H10+K10+N10 -> 790 | Q10: =Q9+P10 -> 5585 | R10: =Q10-MAX(0,MAX($Q$2:Q10)) -> 0
A11: 42670 | B11: =YEAR(A11) -> 2016 | C11: =MONTH(A11) -> 10 | D11: Thursday | E11: 8607.1 | F11: 14.45 | G11: 50.1 | H11: -1250 | I11: 2 | J11: 48.6 | K11: -1219 | L11: 2 | M11: 47.2 | N11: -6 | O11: 1 | P11: =H11+K11+N11 -> -2475 | Q11: =Q10+P11 -> 3110 | R11: =Q11-MAX(0,MAX($Q$2:Q11)) -> -2475
A12: 42698 | B12: =YEAR(A12) -> 2016 | C12: =MONTH(A12) -> 11 | D12: Thursday | E12: 8011.8 | F12: 18.04 | G12: 55.7 | H12: -966 | I12: 1 | J12: 54.1 | K12: -1332 | L12: 2 | M12: 50.8 | N12: 675 | O12: 1 | P12: =H12+K12+N12 -> -1623 | Q12: =Q11+P12 -> 1487 | R12: =Q12-MAX(0,MAX($Q$2:Q12)) -> -4098
A13: 42733 | B13: =YEAR(A13) -> 2016 | C13: =MONTH(A13) -> 12 | D13: Thursday | E13: 8030.6 | F13: 15.54 | G13: 54.2 | H13: 816 | I13: 1 | J13: 53.2 | K13: 1031 | L13: 1 | M13: 50.9 | N13: 980 | O13: 1 | P13: =H13+K13+N13 -> 2827 | Q13: =Q12+P13 -> 4314 | R13: =Q13-MAX(0,MAX($Q$2:Q13)) -> -1271
A14: 42760 | B14: =YEAR(A14) -> 2017 | C14: =MONTH(A14) -> 1 | D14: Wednesday | E14: 8499.4 | F14: 15.29 | G14: 37.5 | H14: 611 | I14: 1 | J14: 38.7 | K14: -1016 | L14: 2 | M14: 37.1 | N14: -985 | O14: 2 | P14: =H14+K14+N14 -> -1390 | Q14: =Q13+P14 -> 2924 | R14: =Q14-MAX(0,MAX($Q$2:Q14)) -> -2661
... A440: 46314 | B440: =YEAR(A440) -> 2026 | C440: =MONTH(A440) -> 10 | D440: Monday | E440: 23150.8 | F440: 14.06 | G440: 203 | H440: 5207 | I440: 1 | J440: 198.6 | K440: -4289 | L440: 2 | M440: 190.7 | N440: 5076 | O440: 1 | P440: =H440+K440+N440 -> 5994 | Q440: =Q439+P440 -> 1327936 | R440: =Q440-MAX(0,MAX($Q$2:Q440)) -> 0

Sheet Set B daily
A1: Date | B1: Year | C1: Month | D1: Day | E1: Nifty open | F1: VIX (prev close) | G1: 09:45 premium (pts) | H1: 09:45 P&L ₹ | I1: 09:45 legs stopped | J1: 10:05 premium (pts) | K1: 10:05 P&L ₹ | L1: 10:05 legs stopped | M1: 10:35 premium (pts) | N1: 10:35 P&L ₹ | O1: 10:35 legs stopped | P1: Total P&L ₹ (3 lots) | Q1: Cumulative ₹ | R1: Drawdown ₹
A2: 42397 | B2: =YEAR(A2) -> 2016 | C2: =MONTH(A2) -> 1 | D2: Thursday | E2: 7426.5 | F2: 19.06 | G2: 35.3 | H2: -947 | I2: 2 | J2: 36 | K2: -535 | L2: 1 | M2: 32 | N2: -880 | O2: 2 | P2: =H2+K2+N2 -> -2362 | Q2: =P2 -> -2362 | R2: =Q2-MAX(0,MAX($Q$2:Q2)) -> -2362
A3: 42425 | B3: =YEAR(A3) -> 2016 | C3: =MONTH(A3) -> 2 | D3: Thursday | E3: 7029.8 | F3: 22.96 | G3: 53.3 | H3: 1642 | I3: 1 | J3: 51 | K3: -1268 | L3: 2 | M3: 51.2 | N3: 1868 | O3: 1 | P3: =H3+K3+N3 -> 2242 | Q3: =Q2+P3 -> -120 | R3: =Q3-MAX(0,MAX($Q$2:Q3)) -> -120
A4: 42460 | B4: =YEAR(A4) -> 2016 | C4: =MONTH(A4) -> 3 | D4: Thursday | E4: 7727.6 | F4: 16.81 | G4: 35.6 | H4: -953 | I4: 2 | J4: 36.7 | K4: 1296 | L4: 1 | M4: 35.1 | N4: 1251 | O4: 1 | P4: =H4+K4+N4 -> 1594 | Q4: =Q3+P4 -> 1474 | R4: =Q4-MAX(0,MAX($Q$2:Q4)) -> 0
A5: 42488 | B5: =YEAR(A5) -> 2016 | C5: =MONTH(A5) -> 4 | D5: Thursday | E5: 7967.4 | F5: 16.35 | G5: 41.4 | H5: -1071 | I5: 2 | J5: 37.7 | K5: 274 | L5: 1 | M5: 41.3 | N5: 1818 | O5: 1 | P5: =H5+K5+N5 -> 1021 | Q5: =Q4+P5 -> 2495 | R5: =Q5-MAX(0,MAX($Q$2:Q5)) -> 0
A6: 42516 | B6: =YEAR(A6) -> 2016 | C6: =MONTH(A6) -> 5 | D6: Thursday | E6: 7974.4 | F6: 15.52 | G6: 46.7 | H6: -238 | I6: 1 | J6: 46 | K6: -1165 | L6: 2 | M6: 42 | N6: -1085 | O6: 2 | P6: =H6+K6+N6 -> -2488 | Q6: =Q5+P6 -> 7 | R6: =Q6-MAX(0,MAX($Q$2:Q6)) -> -2488
A7: 42551 | B7: =YEAR(A7) -> 2016 | C7: =MONTH(A7) -> 6 | D7: Thursday | E7: 8262.3 | F7: 16.16 | G7: 54.7 | H7: 305 | I7: 1 | J7: 55 | K7: -1350 | L7: 2 | M7: 52.5 | N7: -1299 | O7: 2 | P7: =H7+K7+N7 -> -2344 | Q7: =Q6+P7 -> -2337 | R7: =Q7-MAX(0,MAX($Q$2:Q7)) -> -4832
A8: 42579 | B8: =YEAR(A8) -> 2016 | C8: =MONTH(A8) -> 7 | D8: Thursday | E8: 8636.8 | F8: 15.43 | G8: 45.5 | H8: 1494 | I8: 0 | J8: 44.4 | K8: 1421 | L8: 0 | M8: 42.4 | N8: 1155 | O8: 1 | P8: =H8+K8+N8 -> 4070 | Q8: =Q7+P8 -> 1733 | R8: =Q8-MAX(0,MAX($Q$2:Q8)) -> -762
A9: 42607 | B9: =YEAR(A9) -> 2016 | C9: =MONTH(A9) -> 8 | D9: Thursday | E9: 8666.8 | F9: 13.49 | G9: 57.8 | H9: 116 | I9: 1 | J9: 56.8 | K9: 2091 | L9: 1 | M9: 54.8 | N9: 2090 | O9: 1 | P9: =H9+K9+N9 -> 4297 | Q9: =Q8+P9 -> 6030 | R9: =Q9-MAX(0,MAX($Q$2:Q9)) -> 0
A10: 42642 | B10: =YEAR(A10) -> 2016 | C10: =MONTH(A10) -> 9 | D10: Thursday | E10: 8790.8 | F10: 13.85 | G10: 40.6 | H10: 297 | I10: 1 | J10: 40.5 | K10: 61 | L10: 1 | M10: 41 | N10: -247 | O10: 1 | P10: =H10+K10+N10 -> 111 | Q10: =Q9+P10 -> 6141 | R10: =Q10-MAX(0,MAX($Q$2:Q10)) -> 0
A11: 42670 | B11: =YEAR(A11) -> 2016 | C11: =MONTH(A11) -> 10 | D11: Thursday | E11: 8607.1 | F11: 14.45 | G11: 46.8 | H11: -1181 | I11: 2 | J11: 47.2 | K11: -6 | L11: 1 | M11: 47.1 | N11: -1189 | O11: 2 | P11: =H11+K11+N11 -> -2376 | Q11: =Q10+P11 -> 3765 | R11: =Q11-MAX(0,MAX($Q$2:Q11)) -> -2376
A12: 42698 | B12: =YEAR(A12) -> 2016 | C12: =MONTH(A12) -> 11 | D12: Thursday | E12: 8011.8 | F12: 18.04 | G12: 52.9 | H12: 482 | I12: 1 | J12: 50.8 | K12: 675 | L12: 1 | M12: 48.6 | N12: 526 | O12: 1 | P12: =H12+K12+N12 -> 1683 | Q12: =Q11+P12 -> 5448 | R12: =Q12-MAX(0,MAX($Q$2:Q12)) -> -693
A13: 42733 | B13: =YEAR(A13) -> 2016 | C13: =MONTH(A13) -> 12 | D13: Thursday | E13: 8030.6 | F13: 15.54 | G13: 52.4 | H13: 982 | I13: 1 | J13: 50.9 | K13: 980 | L13: 1 | M13: 48.5 | N13: 808 | O13: 1 | P13: =H13+K13+N13 -> 2770 | Q13: =Q12+P13 -> 8218 | R13: =Q13-MAX(0,MAX($Q$2:Q13)) -> 0
A14: 42760 | B14: =YEAR(A14) -> 2017 | C14: =MONTH(A14) -> 1 | D14: Wednesday | E14: 8499.4 | F14: 15.29 | G14: 39.8 | H14: -1040 | I14: 2 | J14: 37.1 | K14: -985 | L14: 2 | M14: 38.1 | N14: -312 | O14: 1 | P14: =H14+K14+N14 -> -2337 | Q14: =Q13+P14 -> 5881 | R14: =Q14-MAX(0,MAX($Q$2:Q14)) -> -2337
... A440: 46314 | B440: =YEAR(A440) -> 2026 | C440: =MONTH(A440) -> 10 | D440: Monday | E440: 23150.8 | F440: 14.06 | G440: 196.2 | H440: 4181 | I440: 1 | J440: 190.7 | K440: 5076 | L440: 1 | M440: 181.4 | N440: 3141 | O440: 1 | P440: =H440+K440+N440 -> 12398 | Q440: =Q439+P440 -> 1454534 | R440: =Q440-MAX(0,MAX($Q$2:Q440)) -> 0

Sheet Monthly
A1: Set A 9:22+9:35+10:05 — monthly P&L ₹ (3 lots)
A2: Year | B2: Jan | C2: Feb | D2: Mar | E2: Apr | F2: May | G2: Jun | H2: Jul | I2: Aug | J2: Sep | K2: Oct | L2: Nov | M2: Dec | N2: Year total | O2: Expiry days | P2: Winning days
A3: 2016 | B3: =SUMIFS('Set A daily'!$P$2:$P$440,'Set A daily'!$B$2:$B$440,2016,'Set A daily'!$C$2:$C$440,1) -> -2146 | C3: =SUMIFS('Set A daily'!$P$2:$P$440,'Set A daily'!$B$2:$B$440,2016,'Set A daily'!$C$2:$C$440,2) -> -960 | D3: =SUMIFS('Set A daily'!$P$2:$P$440,'Set A daily'!$B$2:$B$440,2016,'Set A daily'!$C$2:$C$440,3) -> -618 | E3: =SUMIFS('Set A daily'!$P$2:$P$440,'Set A daily'!$B$2:$B$440,2016,'Set A daily'!$C$2:$C$440,4) -> -683 | F3: =SUMIFS('Set A daily'!$P$2:$P$440,'Set A daily'!$B$2:$B$440,2016,'Set A daily'!$C$2:$C$440,5) -> -757 | G3: =SUMIFS('Set A daily'!$P$2:$P$440,'Set A daily'!$B$2:$B$440,2016,'Set A daily'!$C$2:$C$440,6) -> -755 | H3: =SUMIFS('Set A daily'!$P$2:$P$440,'Set A daily'!$B$2:$B$440,2016,'Set A daily'!$C$2:$C$440,7) -> 4484 | I3: =SUMIFS('Set A daily'!$P$2:$P$440,'Set A daily'!$B$2:$B$440,2016,'Set A daily'!$C$2:$C$440,8) -> 6230 | J3: =SUMIFS('Set A daily'!$P$2:$P$440,'Set A daily'!$B$2:$B$440,2016,'Set A daily'!$C$2:$C$440,9) -> 790 | K3: =SUMIFS('Set A daily'!$P$2:$P$440,'Set A daily'!$B$2:$B$440,2016,'Set A daily'!$C$2:$C$440,10) -> -2475 | L3: =SUMIFS('Set A daily'!$P$2:$P$440,'Set A daily'!$B$2:$B$440,2016,'Set A daily'!$C$2:$C$440,11) -> -1623 | M3: =SUMIFS('Set A daily'!$P$2:$P$440,'Set A daily'!$B$2:$B$440,2016,'Set A daily'!$C$2:$C$440,12) -> 2827 | N3: =SUM(B3:M3) -> 4314 | O3: =COUNTIFS('Set A daily'!$B$2:$B$440,2016) -> 12 | P3: =COUNTIFS('Set A daily'!$B$2:$B$440,2016,'Set A daily'!$P$2:$P$440,">0") -> 4
A4: 2017 | B4: =SUMIFS('Set A daily'!$P$2:$P$440,'Set A daily'!$B$2:$B$440,2017,'Set A daily'!$C$2:$C$440,1) -> -1390 | C4: =SUMIFS('Set A daily'!$P$2:$P$440,'Set A daily'!$B$2:$B$440,2017,'Set A daily'!$C$2:$C$440,2) -> 3347 | D4: =SUMIFS('Set A daily'!$P$2:$P$440,'Set A daily'!$B$2:$B$440,2017,'Set A daily'!$C$2:$C$440,3) -> 114 | E4: =SUMIFS('Set A daily'!$P$2:$P$440,'Set A daily'!$B$2:$B$440,2017,'Set A daily'!$C$2:$C$440,4) -> 2041 | F4: =SUMIFS('Set A daily'!$P$2:$P$440,'Set A daily'!$B$2:$B$440,2017,'Set A daily'!$C$2:$C$440,5) -> 2890 | G4: =SUMIFS('Set A daily'!$P$2:$P$440,'Set A daily'!$B$2:$B$440,2017,'Set A daily'!$C$2:$C$440,6) -> -856 | H4: =SUMIFS('Set A daily'!$P$2:$P$440,'Set A daily'!$B$2:$B$440,2017,'Set A daily'!$C$2:$C$440,7) -> -4025 | I4: =SUMIFS('Set A daily'!$P$2:$P$440,'Set A daily'!$B$2:$B$440,2017,'Set A daily'!$C$2:$C$440,8) -> 1066 | J4: =SUMIFS('Set A daily'!$P$2:$P$440,'Set A daily'!$B$2:$B$440,2017,'Set A daily'!$C$2:$C$440,9) -> -1781 | K4: =SUMIFS('Set A daily'!$P$2:$P$440,'Set A daily'!$B$2:$B$440,2017,'Set A daily'!$C$2:$C$440,10) -> 4958 | L4: =SUMIFS('Set A daily'!$P$2:$P$440,'Set A daily'!$B$2:$B$440,2017,'Set A daily'!$C$2:$C$440,11) -> 2899 | M4: =SUMIFS('Set A daily'!$P$2:$P$440,'Set A daily'!$B$2:$B$440,2017,'Set A daily'!$C$2:$C$440,12) -> 2227 | N4: =SUM(B4:M4) -> 11490 | O4: =COUNTIFS('Set A daily'!$B$2:$B$440,2017) -> 12 | P4: =COUNTIFS('Set A daily'!$B$2:$B$440,2017,'Set A daily'!$P$2:$P$440,">0") -> 8
A5: 2018 | B5: =SUMIFS('Set A daily'!$P$2:$P$440,'Set A daily'!$B$2:$B$440,2018,'Set A daily'!$C$2:$C$440,1) -> -794 | C5: =SUMIFS('Set A daily'!$P$2:$P$440,'Set A daily'!$B$2:$B$440,2018,'Set A daily'!$C$2:$C$440,2) -> 2875 | D5: =SUMIFS('Set A daily'!$P$2:$P$440,'Set A daily'!$B$2:$B$440,2018,'Set A daily'!$C$2:$C$440,3) -> 239 | E5: =SUMIFS('Set A daily'!$P$2:$P$440,'Set A daily'!$B$2:$B$440,2018,'Set A daily'!$C$2:$C$440,4) -> -3288 | F5: =SUMIFS('Set A daily'!$P$2:$P$440,'Set A daily'!$B$2:$B$440,2018,'Set A daily'!$C$2:$C$440,5) -> -767 | G5: =SUMIFS('Set A daily'!$P$2:$P$440,'Set A daily'!$B$2:$B$440,2018,'Set A daily'!$C$2:$C$440,6) -> -1261 | H5: =SUMIFS('Set A daily'!$P$2:$P$440,'Set A daily'!$B$2:$B$440,2018,'Set A daily'!$C$2:$C$440,7) -> -289 | I5: =SUMIFS('Set A daily'!$P$2:$P$440,'Set A daily'!$B$2:$B$440,2018,'Set A daily'!$C$2:$C$440,8) -> 1368 | J5: =SUMIFS('Set A daily'!$P$2:$P$440,'Set A daily'!$B$2:$B$440,2018,'Set A daily'!$C$2:$C$440,9) -> 5784 | K5: =SUMIFS('Set A daily'!$P$2:$P$440,'Set A daily'!$B$2:$B$440,2018,'Set A daily'!$C$2:$C$440,10) -> 3759 | L5: =SUMIFS('Set A daily'!$P$2:$P$440,'Set A daily'!$B$2:$B$440,2018,'Set A daily'!$C$2:$C$440,11) -> 2701 | M5: =SUMIFS('Set A daily'!$P$2:$P$440,'Set A daily'!$B$2:$B$440,2018,'Set A daily'!$C$2:$C$440,12) -> 4668 | N5: =SUM(B5:M5) -> 14995 | O5: =COUNTIFS('Set A daily'!$B$2:$B$440,2018) -> 12 | P5: =COUNTIFS('Set A daily'!$B$2:$B$440,2018,'Set A daily'!$P$2:$P$440,">0") -> 7
A6: 2019 | B6: =SUMIFS('Set A daily'!$P$2:$P$440,'Set A daily'!$B$2:$B$440,2019,'Set A daily'!$C$2:$C$440,1) -> -1464 | C6: =SUMIFS('Set A daily'!$P$2:$P$440,'Set A daily'!$B$2:$B$440,2019,'Set A daily'!$C$2:$C$440,2) -> 8677 | D6: =SUMIFS('Set A daily'!$P$2:$P$440,'Set A daily'!$B$2:$B$440,2019,'Set A daily'!$C$2:$C$440,3) -> 4493 | E6: =SUMIFS('Set A daily'!$P$2:$P$440,'Set A daily'!$B$2:$B$440,2019,'Set A daily'!$C$2:$C$440,4) -> 2647 | F6: =SUMIFS('Set A daily'!$P$2:$P$440,'Set A daily'!$B$2:$B$440,2019,'Set A daily'!$C$2:$C$440,5) -> 18782 | G6: =SUMIFS('Set A daily'!$P$2:$P$440,'Set A daily'!$B$2:$B$440,2019,'Set A daily'!$C$2:$C$440,6) -> -172 | H6: =SUMIFS('Set A daily'!$P$2:$P$440,'Set A daily'!$B$2:$B$440,2019,'Set A daily'!$C$2:$C$440,7) -> 8757 | I6: =SUMIFS('Set A daily'!$P$2:$P$440,'Set A daily'!$B$2:$B$440,2019,'Set A daily'!$C$2:$C$440,8) -> 7457 | J6: =SUMIFS('Set A daily'!$P$2:$P$440,'Set A daily'!$B$2:$B$440,2019,'Set A daily'!$C$2:$C$440,9) -> 10428 | K6: =SUMIFS('Set A daily'!$P$2:$P$440,'Set A daily'!$B$2:$B$440,2019,'Set A daily'!$C$2:$C$440,10) -> 5788 | L6: =SUMIFS('Set A daily'!$P$2:$P$440,'Set A daily'!$B$2:$B$440,2019,'Set A daily'!$C$2:$C$440,11) -> 911 | M6: =SUMIFS('Set A daily'!$P$2:$P$440,'Set A daily'!$B$2:$B$440,2019,'Set A daily'!$C$2:$C$440,12) -> 7603 | N6: =SUM(B6:M6) -> 73907 | O6: =COUNTIFS('Set A daily'!$B$2:$B$440,2019) -> 47 | P6: =COUNTIFS('Set A daily'!$B$2:$B$440,2019,'Set A daily'!$P$2:$P$440,">0") -> 33
A7: 2020 | B7: =SUMIFS('Set A daily'!$P$2:$P$440,'Set A daily'!$B$2:$B$440,2020,'Set A daily'!$C$2:$C$440,1) -> -2885 | C7: =SUMIFS('Set A daily'!$P$2:$P$440,'Set A daily'!$B$2:$B$440,2020,'Set A daily'!$C$2:$C$440,2) -> -8060 | D7: =SUMIFS('Set A daily'!$P$2:$P$440,'Set A daily'!$B$2:$B$440,2020,'Set A daily'!$C$2:$C$440,3) -> 29645 | E7: =SUMIFS('Set A daily'!$P$2:$P$440,'Set A daily'!$B$2:$B$440,2020,'Set A daily'!$C$2:$C$440,4) -> 29464 | F7: =SUMIFS('Set A daily'!$P$2:$P$440,'Set A daily'!$B$2:$B$440,2020,'Set A daily'!$C$2:$C$440,5) -> 25266 | G7: =SUMIFS('Set A daily'!$P$2:$P$440,'Set A daily'!$B$2:$B$440,2020,'Set A daily'!$C$2:$C$440,6) -> 1877 | H7: =SUMIFS('Set A daily'!$P$2:$P$440,'Set A daily'!$B$2:$B$440,2020,'Set A daily'!$C$2:$C$440,7) -> 5255 | I7: =SUMIFS('Set A daily'!$P$2:$P$440,'Set A daily'!$B$2:$B$440,2020,'Set A daily'!$C$2:$C$440,8) -> 10292 | J7: =SUMIFS('Set A daily'!$P$2:$P$440,'Set A daily'!$B$2:$B$440,2020,'Set A daily'!$C$2:$C$440,9) -> 13423 | K7: =SUMIFS('Set A daily'!$P$2:$P$440,'Set A daily'!$B$2:$B$440,2020,'Set A daily'!$C$2:$C$440,10) -> 12283 | L7: =SUMIFS('Set A daily'!$P$2:$P$440,'Set A daily'!$B$2:$B$440,2020,'Set A daily'!$C$2:$C$440,11) -> 6387 | M7: =SUMIFS('Set A daily'!$P$2:$P$440,'Set A daily'!$B$2:$B$440,2020,'Set A daily'!$C$2:$C$440,12) -> 18792 | N7: =SUM(B7:M7) -> 141739 | O7: =COUNTIFS('Set A daily'!$B$2:$B$440,2020) -> 53 | P7: =COUNTIFS('Set A daily'!$B$2:$B$440,2020,'Set A daily'!$P$2:$P$440,">0") -> 37
A8: 2021 | B8: =SUMIFS('Set A daily'!$P$2:$P$440,'Set A daily'!$B$2:$B$440,2021,'Set A daily'!$C$2:$C$440,1) -> 5034 | C8: =SUMIFS('Set A daily'!$P$2:$P$440,'Set A daily'!$B$2:$B$440,2021,'Set A daily'!$C$2:$C$440,2) -> 23741 | D8: =SUMIFS('Set A daily'!$P$2:$P$440,'Set A daily'!$B$2:$B$440,2021,'Set A daily'!$C$2:$C$440,3) -> 11502 | E8: =SUMIFS('Set A daily'!$P$2:$P$440,'Set A daily'!$B$2:$B$440,2021,'Set A daily'!$C$2:$C$440,4) -> 6129 | F8: =SUMIFS('Set A daily'!$P$2:$P$440,'Set A daily'!$B$2:$B$440,2021,'Set A daily'!$C$2:$C$440,5) -> 15621 | G8: =SUMIFS('Set A daily'!$P$2:$P$440,'Set A daily'!$B$2:$B$440,2021,'Set A daily'!$C$2:$C$440,6) -> 10314 | H8: =SUMIFS('Set A daily'!$P$2:$P$440,'Set A daily'!$B$2:$B$440,2021,'Set A daily'!$C$2:$C$440,7) -> 13946 | I8: =SUMIFS('Set A daily'!$P$2:$P$440,'Set A daily'!$B$2:$B$440,2021,'Set A daily'!$C$2:$C$440,8) -> 8180 | J8: =SUMIFS('Set A daily'!$P$2:$P$440,'Set A daily'!$B$2:$B$440,2021,'Set A daily'!$C$2:$C$440,9) -> 10546 | K8: =SUMIFS('Set A daily'!$P$2:$P$440,'Set A daily'!$B$2:$B$440,2021,'Set A daily'!$C$2:$C$440,10) -> 22222 | L8: =SUMIFS('Set A daily'!$P$2:$P$440,'Set A daily'!$B$2:$B$440,2021,'Set A daily'!$C$2:$C$440,11) -> 21451 | M8: =SUMIFS('Set A daily'!$P$2:$P$440,'Set A daily'!$B$2:$B$440,2021,'Set A daily'!$C$2:$C$440,12) -> 18647 | N8: =SUM(B8:M8) -> 167333 | O8: =COUNTIFS('Set A daily'!$B$2:$B$440,2021) -> 52 | P8: =COUNTIFS('Set A daily'!$B$2:$B$440,2021,'Set A daily'!$P$2:$P$440,">0") -> 41
A9: 2022 | B9: =SUMIFS('Set A daily'!$P$2:$P$440,'Set A daily'!$B$2:$B$440,2022,'Set A daily'!$C$2:$C$440,1) -> 2763 | C9: =SUMIFS('Set A daily'!$P$2:$P$440,'Set A daily'!$B$2:$B$440,2022,'Set A daily'!$C$2:$C$440,2) -> 1019 | D9: =SUMIFS('Set A daily'!$P$2:$P$440,'Set A daily'!$B$2:$B$440,2022,'Set A daily'!$C$2:$C$440,3) -> 30847 | E9: =SUMIFS('Set A daily'!$P$2:$P$440,'Set A daily'!$B$2:$B$440,2022,'Set A daily'!$C$2:$C$440,4) -> 8463 | F9: =SUMIFS('Set A daily'!$P$2:$P$440,'Set A daily'!$B$2:$B$440,2022,'Set A daily'!$C$2:$C$440,5) -> -3473 | G9: =SUMIFS('Set A daily'!$P$2:$P$440,'Set A daily'!$B$2:$B$440,2022,'Set A daily'!$C$2:$C$440,6) -> 15923 | H9: =SUMIFS('Set A daily'!$P$2:$P$440,'Set A daily'!$B$2:$B$440,2022,'Set A daily'!$C$2:$C$440,7) -> 36923 | I9: =SUMIFS('Set A daily'!$P$2:$P$440,'Set A daily'!$B$2:$B$440,2022,'Set A daily'!$C$2:$C$440,8) -> 16290 | J9: =SUMIFS('Set A daily'!$P$2:$P$440,'Set A daily'!$B$2:$B$440,2022,'Set A daily'!$C$2:$C$440,9) -> 31337 | K9: =SUMIFS('Set A daily'!$P$2:$P$440,'Set A daily'!$B$2:$B$440,2022,'Set A daily'!$C$2:$C$440,10) -> 25818 | L9: =SUMIFS('Set A daily'!$P$2:$P$440,'Set A daily'!$B$2:$B$440,2022,'Set A daily'!$C$2:$C$440,11) -> 18678 | M9: =SUMIFS('Set A daily'!$P$2:$P$440,'Set A daily'!$B$2:$B$440,2022,'Set A daily'!$C$2:$C$440,12) -> 11471 | N9: =SUM(B9:M9) -> 196059 | O9: =COUNTIFS('Set A daily'!$B$2:$B$440,2022) -> 52 | P9: =COUNTIFS('Set A daily'!$B$2:$B$440,2022,'Set A daily'!$P$2:$P$440,">0") -> 41
A10: 2023 | B10: =SUMIFS('Set A daily'!$P$2:$P$440,'Set A daily'!$B$2:$B$440,2023,'Set A daily'!$C$2:$C$440,1) -> 8360 | C10: =SUMIFS('Set A daily'!$P$2:$P$440,'Set A daily'!$B$2:$B$440,2023,'Set A daily'!$C$2:$C$440,2) -> 5736 | D10: =SUMIFS('Set A daily'!$P$2:$P$440,'Set A daily'!$B$2:$B$440,2023,'Set A daily'!$C$2:$C$440,3) -> -531 | E10: =SUMIFS('Set A daily'!$P$2:$P$440,'Set A daily'!$B$2:$B$440,2023,'Set A daily'!$C$2:$C$440,4) -> 5738 | F10: =SUMIFS('Set A daily'!$P$2:$P$440,'Set A daily'!$B$2:$B$440,2023,'Set A daily'!$C$2:$C$440,5) -> -512 | G10: =SUMIFS('Set A daily'!$P$2:$P$440,'Set A daily'!$B$2:$B$440,2023,'Set A daily'!$C$2:$C$440,6) -> -2938 | H10: =SUMIFS('Set A daily'!$P$2:$P$440,'Set A daily'!$B$2:$B$440,2023,'Set A daily'!$C$2:$C$440,7) -> 2733 | I10: =SUMIFS('Set A daily'!$P$2:$P$440,'Set A daily'!$B$2:$B$440,2023,'Set A daily'!$C$2:$C$440,8) -> -607 | J10: =SUMIFS('Set A daily'!$P$2:$P$440,'Set A daily'!$B$2:$B$440,2023,'Set A daily'!$C$2:$C$440,9) -> 10911 | K10: =SUMIFS('Set A daily'!$P$2:$P$440,'Set A daily'!$B$2:$B$440,2023,'Set A daily'!$C$2:$C$440,10) -> 178 | L10: =SUMIFS('Set A daily'!$P$2:$P$440,'Set A daily'!$B$2:$B$440,2023,'Set A daily'!$C$2:$C$440,11) -> 20132 | M10: =SUMIFS('Set A daily'!$P$2:$P$440,'Set A daily'!$B$2:$B$440,2023,'Set A daily'!$C$2:$C$440,12) -> 12154 | N10: =SUM(B10:M10) -> 61354 | O10: =COUNTIFS('Set A daily'!$B$2:$B$440,2023) -> 52 | P10: =COUNTIFS('Set A daily'!$B$2:$B$440,2023,'Set A daily'!$P$2:$P$440,">0") -> 34
A11: 2024 | B11: =SUMIFS('Set A daily'!$P$2:$P$440,'Set A daily'!$B$2:$B$440,2024,'Set A daily'!$C$2:$C$440,1) -> 15005 | C11: =SUMIFS('Set A daily'!$P$2:$P$440,'Set A daily'!$B$2:$B$440,2024,'Set A daily'!$C$2:$C$440,2) -> 36483 | D11: =SUMIFS('Set A daily'!$P$2:$P$440,'Set A daily'!$B$2:$B$440,2024,'Set A daily'!$C$2:$C$440,3) -> -297 | E11: =SUMIFS('Set A daily'!$P$2:$P$440,'Set A daily'!$B$2:$B$440,2024,'Set A daily'!$C$2:$C$440,4) -> -5028 | F11: =SUMIFS('Set A daily'!$P$2:$P$440,'Set A daily'!$B$2:$B$440,2024,'Set A daily'!$C$2:$C$440,5) -> 43540 | G11: =SUMIFS('Set A daily'!$P$2:$P$440,'Set A daily'!$B$2:$B$440,2024,'Set A daily'!$C$2:$C$440,6) -> 31119 | H11: =SUMIFS('Set A daily'!$P$2:$P$440,'Set A daily'!$B$2:$B$440,2024,'Set A daily'!$C$2:$C$440,7) -> 19220 | I11: =SUMIFS('Set A daily'!$P$2:$P$440,'Set A daily'!$B$2:$B$440,2024,'Set A daily'!$C$2:$C$440,8) -> 35502 | J11: =SUMIFS('Set A daily'!$P$2:$P$440,'Set A daily'!$B$2:$B$440,2024,'Set A daily'!$C$2:$C$440,9) -> 9671 | K11: =SUMIFS('Set A daily'!$P$2:$P$440,'Set A daily'!$B$2:$B$440,2024,'Set A daily'!$C$2:$C$440,10) -> 22490 | L11: =SUMIFS('Set A daily'!$P$2:$P$440,'Set A daily'!$B$2:$B$440,2024,'Set A daily'!$C$2:$C$440,11) -> 31700 | M11: =SUMIFS('Set A daily'!$P$2:$P$440,'Set A daily'!$B$2:$B$440,2024,'Set A daily'!$C$2:$C$440,12) -> 9520 | N11: =SUM(B11:M11) -> 248925 | O11: =COUNTIFS('Set A daily'!$B$2:$B$440,2024) -> 52 | P11: =COUNTIFS('Set A daily'!$B$2:$B$440,2024,'Set A daily'!$P$2:$P$440,">0") -> 38
A12: 2025 | B12: =SUMIFS('Set A daily'!$P$2:$P$440,'Set A daily'!$B$2:$B$440,2025,'Set A daily'!$C$2:$C$440,1) -> 36737 | C12: =SUMIFS('Set A daily'!$P$2:$P$440,'Set A daily'!$B$2:$B$440,2025,'Set A daily'!$C$2:$C$440,2) -> 25096 | D12: =SUMIFS('Set A daily'!$P$2:$P$440,'Set A daily'!$B$2:$B$440,2025,'Set A daily'!$C$2:$C$440,3) -> -3176 | E12: =SUMIFS('Set A daily'!$P$2:$P$440,'Set A daily'!$B$2:$B$440,2025,'Set A daily'!$C$2:$C$440,4) -> 53280 | F12: =SUMIFS('Set A daily'!$P$2:$P$440,'Set A daily'!$B$2:$B$440,2025,'Set A daily'!$C$2:$C$440,5) -> 21782 | G12: =SUMIFS('Set A daily'!$P$2:$P$440,'Set A daily'!$B$2:$B$440,2025,'Set A daily'!$C$2:$C$440,6) -> 11312 | H12: =SUMIFS('Set A daily'!$P$2:$P$440,'Set A daily'!$B$2:$B$440,2025,'Set A daily'!$C$2:$C$440,7) -> 12615 | I12: =SUMIFS('Set A daily'!$P$2:$P$440,'Set A daily'!$B$2:$B$440,2025,'Set A daily'!$C$2:$C$440,8) -> -5290 | J12: =SUMIFS('Set A daily'!$P$2:$P$440,'Set A daily'!$B$2:$B$440,2025,'Set A daily'!$C$2:$C$440,9) -> 9623 | K12: =SUMIFS('Set A daily'!$P$2:$P$440,'Set A daily'!$B$2:$B$440,2025,'Set A daily'!$C$2:$C$440,10) -> 11925 | L12: =SUMIFS('Set A daily'!$P$2:$P$440,'Set A daily'!$B$2:$B$440,2025,'Set A daily'!$C$2:$C$440,11) -> 2047 | M12: =SUMIFS('Set A daily'!$P$2:$P$440,'Set A daily'!$B$2:$B$440,2025,'Set A daily'!$C$2:$C$440,12) -> 24084 | N12: =SUM(B12:M12) -> 200035 | O12: =COUNTIFS('Set A daily'!$B$2:$B$440,2025) -> 53 | P12: =COUNTIFS('Set A daily'!$B$2:$B$440,2025,'Set A daily'!$P$2:$P$440,">0") -> 36
A13: 2026 | B13: =SUMIFS('Set A daily'!$P$2:$P$440,'Set A daily'!$B$2:$B$440,2026,'Set A daily'!$C$2:$C$440,1) -> 13339 | C13: =SUMIFS('Set A daily'!$P$2:$P$440,'Set A daily'!$B$2:$B$440,2026,'Set A daily'!$C$2:$C$440,2) -> 53280 | D13: =SUMIFS('Set A daily'!$P$2:$P$440,'Set A daily'!$B$2:$B$440,2026,'Set A daily'!$C$2:$C$440,3) -> 50140 | E13: =SUMIFS('Set A daily'!$P$2:$P$440,'Set A daily'!$B$2:$B$440,2026,'Set A daily'!$C$2:$C$440,4) -> 35270 | F13: =SUMIFS('Set A daily'!$P$2:$P$440,'Set A daily'!$B$2:$B$440,2026,'Set A daily'!$C$2:$C$440,5) -> 15083 | G13: =SUMIFS('Set A daily'!$P$2:$P$440,'Set A daily'!$B$2:$B$440,2026,'Set A daily'!$C$2:$C$440,6) -> 5614 | H13: =SUMIFS('Set A daily'!$P$2:$P$440,'Set A daily'!$B$2:$B$440,2026,'Set A daily'!$C$2:$C$440,7) -> 7521 | I13: =SUMIFS('Set A daily'!$P$2:$P$440,'Set A daily'!$B$2:$B$440,2026,'Set A daily'!$C$2:$C$440,8) -> 11910 | J13: =SUMIFS('Set A daily'!$P$2:$P$440,'Set A daily'!$B$2:$B$440,2026,'Set A daily'!$C$2:$C$440,9) -> 5692 | K13: =SUMIFS('Set A daily'!$P$2:$P$440,'Set A daily'!$B$2:$B$440,2026,'Set A daily'!$C$2:$C$440,10) -> 9936 | L13: =SUMIFS('Set A daily'!$P$2:$P$440,'Set A daily'!$B$2:$B$440,2026,'Set A daily'!$C$2:$C$440,11) -> 0 | M13: =SUMIFS('Set A daily'!$P$2:$P$440,'Set A daily'!$B$2:$B$440,2026,'Set A daily'!$C$2:$C$440,12) -> 0 | N13: =SUM(B13:M13) -> 207785 | O13: =COUNTIFS('Set A daily'!$B$2:$B$440,2026) -> 42 | P13: =COUNTIFS('Set A daily'!$B$2:$B$440,2026,'Set A daily'!$P$2:$P$440,">0") -> 31
A14: Total | B14: =SUM(B3:B13) -> 72559 | C14: =SUM(C3:C13) -> 151234 | D14: =SUM(D3:D13) -> 122358 | E14: =SUM(E3:E13) -> 134033 | F14: =SUM(F3:F13) -> 137455 | G14: =SUM(G3:G13) -> 70177 | H14: =SUM(H3:H13) -> 107140 | I14: =SUM(I3:I13) -> 92398 | ... P14: =SUM(P3:P13) -> 310
A17: Set B 9:45+10:05+10:35 — monthly P&L ₹ (3 lots)
A18: Year | B18: Jan | C18: Feb | D18: Mar | E18: Apr | F18: May | G18: Jun | H18: Jul | I18: Aug | J18: Sep | K18: Oct | L18: Nov | M18: Dec | N18: Year total | O18: Expiry days | P18: Winning days
A19: 2016 | B19: =SUMIFS('Set B daily'!$P$2:$P$440,'Set B daily'!$B$2:$B$440,2016,'Set B daily'!$C$2:$C$440,1) -> -2362 | C19: =SUMIFS('Set B daily'!$P$2:$P$440,'Set B daily'!$B$2:$B$440,2016,'Set B daily'!$C$2:$C$440,2) -> 2242 | D19: =SUMIFS('Set B daily'!$P$2:$P$440,'Set B daily'!$B$2:$B$440,2016,'Set B daily'!$C$2:$C$440,3) -> 1594 | E19: =SUMIFS('Set B daily'!$P$2:$P$440,'Set B daily'!$B$2:$B$440,2016,'Set B daily'!$C$2:$C$440,4) -> 1021 | F19: =SUMIFS('Set B daily'!$P$2:$P$440,'Set B daily'!$B$2:$B$440,2016,'Set B daily'!$C$2:$C$440,5) -> -2488 | G19: =SUMIFS('Set B daily'!$P$2:$P$440,'Set B daily'!$B$2:$B$440,2016,'Set B daily'!$C$2:$C$440,6) -> -2344 | H19: =SUMIFS('Set B daily'!$P$2:$P$440,'Set B daily'!$B$2:$B$440,2016,'Set B daily'!$C$2:$C$440,7) -> 4070 | I19: =SUMIFS('Set B daily'!$P$2:$P$440,'Set B daily'!$B$2:$B$440,2016,'Set B daily'!$C$2:$C$440,8) -> 4297 | J19: =SUMIFS('Set B daily'!$P$2:$P$440,'Set B daily'!$B$2:$B$440,2016,'Set B daily'!$C$2:$C$440,9) -> 111 | K19: =SUMIFS('Set B daily'!$P$2:$P$440,'Set B daily'!$B$2:$B$440,2016,'Set B daily'!$C$2:$C$440,10) -> -2376 | L19: =SUMIFS('Set B daily'!$P$2:$P$440,'Set B daily'!$B$2:$B$440,2016,'Set B daily'!$C$2:$C$440,11) -> 1683 | M19: =SUMIFS('Set B daily'!$P$2:$P$440,'Set B daily'!$B$2:$B$440,2016,'Set B daily'!$C$2:$C$440,12) -> 2770 | N19: =SUM(B19:M19) -> 8218 | O19: =COUNTIFS('Set B daily'!$B$2:$B$440,2016) -> 12 | P19: =COUNTIFS('Set B daily'!$B$2:$B$440,2016,'Set B daily'!$P$2:$P$440,">0") -> 8
A20: 2017 | B20: =SUMIFS('Set B daily'!$P$2:$P$440,'Set B daily'!$B$2:$B$440,2017,'Set B daily'!$C$2:$C$440,1) -> -2337 | C20: =SUMIFS('Set B daily'!$P$2:$P$440,'Set B daily'!$B$2:$B$440,2017,'Set B daily'!$C$2:$C$440,2) -> -1412 | D20: =SUMIFS('Set B daily'!$P$2:$P$440,'Set B daily'!$B$2:$B$440,2017,'Set B daily'!$C$2:$C$440,3) -> -1164 | E20: =SUMIFS('Set B daily'!$P$2:$P$440,'Set B daily'!$B$2:$B$440,2017,'Set B daily'!$C$2:$C$440,4) -> 2367 | F20: =SUMIFS('Set B daily'!$P$2:$P$440,'Set B daily'!$B$2:$B$440,2017,'Set B daily'!$C$2:$C$440,5) -> -409 | G20: =SUMIFS('Set B daily'!$P$2:$P$440,'Set B daily'!$B$2:$B$440,2017,'Set B daily'!$C$2:$C$440,6) -> -749 | H20: =SUMIFS('Set B daily'!$P$2:$P$440,'Set B daily'!$B$2:$B$440,2017,'Set B daily'!$C$2:$C$440,7) -> -3819 | I20: =SUMIFS('Set B daily'!$P$2:$P$440,'Set B daily'!$B$2:$B$440,2017,'Set B daily'!$C$2:$C$440,8) -> 1653 | J20: =SUMIFS('Set B daily'!$P$2:$P$440,'Set B daily'!$B$2:$B$440,2017,'Set B daily'!$C$2:$C$440,9) -> -2399 | K20: =SUMIFS('Set B daily'!$P$2:$P$440,'Set B daily'!$B$2:$B$440,2017,'Set B daily'!$C$2:$C$440,10) -> 5748 | L20: =SUMIFS('Set B daily'!$P$2:$P$440,'Set B daily'!$B$2:$B$440,2017,'Set B daily'!$C$2:$C$440,11) -> 275 | M20: =SUMIFS('Set B daily'!$P$2:$P$440,'Set B daily'!$B$2:$B$440,2017,'Set B daily'!$C$2:$C$440,12) -> -672 | N20: =SUM(B20:M20) -> -2918 | O20: =COUNTIFS('Set B daily'!$B$2:$B$440,2017) -> 12 | P20: =COUNTIFS('Set B daily'!$B$2:$B$440,2017,'Set B daily'!$P$2:$P$440,">0") -> 4
A21: 2018 | B21: =SUMIFS('Set B daily'!$P$2:$P$440,'Set B daily'!$B$2:$B$440,2018,'Set B daily'!$C$2:$C$440,1) -> 733 | C21: =SUMIFS('Set B daily'!$P$2:$P$440,'Set B daily'!$B$2:$B$440,2018,'Set B daily'!$C$2:$C$440,2) -> 2457 | D21: =SUMIFS('Set B daily'!$P$2:$P$440,'Set B daily'!$B$2:$B$440,2018,'Set B daily'!$C$2:$C$440,3) -> 367 | E21: =SUMIFS('Set B daily'!$P$2:$P$440,'Set B daily'!$B$2:$B$440,2018,'Set B daily'!$C$2:$C$440,4) -> -3197 | F21: =SUMIFS('Set B daily'!$P$2:$P$440,'Set B daily'!$B$2:$B$440,2018,'Set B daily'!$C$2:$C$440,5) -> 4271 | G21: =SUMIFS('Set B daily'!$P$2:$P$440,'Set B daily'!$B$2:$B$440,2018,'Set B daily'!$C$2:$C$440,6) -> 1880 | H21: =SUMIFS('Set B daily'!$P$2:$P$440,'Set B daily'!$B$2:$B$440,2018,'Set B daily'!$C$2:$C$440,7) -> -1742 | I21: =SUMIFS('Set B daily'!$P$2:$P$440,'Set B daily'!$B$2:$B$440,2018,'Set B daily'!$C$2:$C$440,8) -> 1236 | J21: =SUMIFS('Set B daily'!$P$2:$P$440,'Set B daily'!$B$2:$B$440,2018,'Set B daily'!$C$2:$C$440,9) -> 5350 | K21: =SUMIFS('Set B daily'!$P$2:$P$440,'Set B daily'!$B$2:$B$440,2018,'Set B daily'!$C$2:$C$440,10) -> 498 | L21: =SUMIFS('Set B daily'!$P$2:$P$440,'Set B daily'!$B$2:$B$440,2018,'Set B daily'!$C$2:$C$440,11) -> 1187 | M21: =SUMIFS('Set B daily'!$P$2:$P$440,'Set B daily'!$B$2:$B$440,2018,'Set B daily'!$C$2:$C$440,12) -> -2844 | N21: =SUM(B21:M21) -> 10196 | O21: =COUNTIFS('Set B daily'!$B$2:$B$440,2018) -> 12 | P21: =COUNTIFS('Set B daily'!$B$2:$B$440,2018,'Set B daily'!$P$2:$P$440,">0") -> 9
A22: 2019 | B22: =SUMIFS('Set B daily'!$P$2:$P$440,'Set B daily'!$B$2:$B$440,2019,'Set B daily'!$C$2:$C$440,1) -> 390 | C22: =SUMIFS('Set B daily'!$P$2:$P$440,'Set B daily'!$B$2:$B$440,2019,'Set B daily'!$C$2:$C$440,2) -> 13921 | D22: =SUMIFS('Set B daily'!$P$2:$P$440,'Set B daily'!$B$2:$B$440,2019,'Set B daily'!$C$2:$C$440,3) -> 515 | E22: =SUMIFS('Set B daily'!$P$2:$P$440,'Set B daily'!$B$2:$B$440,2019,'Set B daily'!$C$2:$C$440,4) -> -943 | F22: =SUMIFS('Set B daily'!$P$2:$P$440,'Set B daily'!$B$2:$B$440,2019,'Set B daily'!$C$2:$C$440,5) -> 19624 | G22: =SUMIFS('Set B daily'!$P$2:$P$440,'Set B daily'!$B$2:$B$440,2019,'Set B daily'!$C$2:$C$440,6) -> -2730 | H22: =SUMIFS('Set B daily'!$P$2:$P$440,'Set B daily'!$B$2:$B$440,2019,'Set B daily'!$C$2:$C$440,7) -> 12935 | I22: =SUMIFS('Set B daily'!$P$2:$P$440,'Set B daily'!$B$2:$B$440,2019,'Set B daily'!$C$2:$C$440,8) -> 11427 | J22: =SUMIFS('Set B daily'!$P$2:$P$440,'Set B daily'!$B$2:$B$440,2019,'Set B daily'!$C$2:$C$440,9) -> 8894 | K22: =SUMIFS('Set B daily'!$P$2:$P$440,'Set B daily'!$B$2:$B$440,2019,'Set B daily'!$C$2:$C$440,10) -> 1871 | L22: =SUMIFS('Set B daily'!$P$2:$P$440,'Set B daily'!$B$2:$B$440,2019,'Set B daily'!$C$2:$C$440,11) -> 4919 | M22: =SUMIFS('Set B daily'!$P$2:$P$440,'Set B daily'!$B$2:$B$440,2019,'Set B daily'!$C$2:$C$440,12) -> 5023 | N22: =SUM(B22:M22) -> 75846 | O22: =COUNTIFS('Set B daily'!$B$2:$B$440,2019) -> 47 | P22: =COUNTIFS('Set B daily'!$B$2:$B$440,2019,'Set B daily'!$P$2:$P$440,">0") -> 34
A23: 2020 | B23: =SUMIFS('Set B daily'!$P$2:$P$440,'Set B daily'!$B$2:$B$440,2020,'Set B daily'!$C$2:$C$440,1) -> 10441 | C23: =SUMIFS('Set B daily'!$P$2:$P$440,'Set B daily'!$B$2:$B$440,2020,'Set B daily'!$C$2:$C$440,2) -> -6993 | D23: =SUMIFS('Set B daily'!$P$2:$P$440,'Set B daily'!$B$2:$B$440,2020,'Set B daily'!$C$2:$C$440,3) -> 37695 | E23: =SUMIFS('Set B daily'!$P$2:$P$440,'Set B daily'!$B$2:$B$440,2020,'Set B daily'!$C$2:$C$440,4) -> 13342 | F23: =SUMIFS('Set B daily'!$P$2:$P$440,'Set B daily'!$B$2:$B$440,2020,'Set B daily'!$C$2:$C$440,5) -> 33207 | G23: =SUMIFS('Set B daily'!$P$2:$P$440,'Set B daily'!$B$2:$B$440,2020,'Set B daily'!$C$2:$C$440,6) -> -2567 | H23: =SUMIFS('Set B daily'!$P$2:$P$440,'Set B daily'!$B$2:$B$440,2020,'Set B daily'!$C$2:$C$440,7) -> -2911 | I23: =SUMIFS('Set B daily'!$P$2:$P$440,'Set B daily'!$B$2:$B$440,2020,'Set B daily'!$C$2:$C$440,8) -> 7871 | J23: =SUMIFS('Set B daily'!$P$2:$P$440,'Set B daily'!$B$2:$B$440,2020,'Set B daily'!$C$2:$C$440,9) -> 17432 | K23: =SUMIFS('Set B daily'!$P$2:$P$440,'Set B daily'!$B$2:$B$440,2020,'Set B daily'!$C$2:$C$440,10) -> 9955 | L23: =SUMIFS('Set B daily'!$P$2:$P$440,'Set B daily'!$B$2:$B$440,2020,'Set B daily'!$C$2:$C$440,11) -> 14937 | M23: =SUMIFS('Set B daily'!$P$2:$P$440,'Set B daily'!$B$2:$B$440,2020,'Set B daily'!$C$2:$C$440,12) -> 12722 | N23: =SUM(B23:M23) -> 145131 | O23: =COUNTIFS('Set B daily'!$B$2:$B$440,2020) -> 53 | P23: =COUNTIFS('Set B daily'!$B$2:$B$440,2020,'Set B daily'!$P$2:$P$440,">0") -> 36
A24: 2021 | B24: =SUMIFS('Set B daily'!$P$2:$P$440,'Set B daily'!$B$2:$B$440,2021,'Set B daily'!$C$2:$C$440,1) -> 21494 | C24: =SUMIFS('Set B daily'!$P$2:$P$440,'Set B daily'!$B$2:$B$440,2021,'Set B daily'!$C$2:$C$440,2) -> 25278 | D24: =SUMIFS('Set B daily'!$P$2:$P$440,'Set B daily'!$B$2:$B$440,2021,'Set B daily'!$C$2:$C$440,3) -> 12900 | E24: =SUMIFS('Set B daily'!$P$2:$P$440,'Set B daily'!$B$2:$B$440,2021,'Set B daily'!$C$2:$C$440,4) -> 4303 | F24: =SUMIFS('Set B daily'!$P$2:$P$440,'Set B daily'!$B$2:$B$440,2021,'Set B daily'!$C$2:$C$440,5) -> 17587 | G24: =SUMIFS('Set B daily'!$P$2:$P$440,'Set B daily'!$B$2:$B$440,2021,'Set B daily'!$C$2:$C$440,6) -> 1103 | H24: =SUMIFS('Set B daily'!$P$2:$P$440,'Set B daily'!$B$2:$B$440,2021,'Set B daily'!$C$2:$C$440,7) -> 14007 | I24: =SUMIFS('Set B daily'!$P$2:$P$440,'Set B daily'!$B$2:$B$440,2021,'Set B daily'!$C$2:$C$440,8) -> 23103 | J24: =SUMIFS('Set B daily'!$P$2:$P$440,'Set B daily'!$B$2:$B$440,2021,'Set B daily'!$C$2:$C$440,9) -> 18131 | K24: =SUMIFS('Set B daily'!$P$2:$P$440,'Set B daily'!$B$2:$B$440,2021,'Set B daily'!$C$2:$C$440,10) -> 26296 | L24: =SUMIFS('Set B daily'!$P$2:$P$440,'Set B daily'!$B$2:$B$440,2021,'Set B daily'!$C$2:$C$440,11) -> 18738 | M24: =SUMIFS('Set B daily'!$P$2:$P$440,'Set B daily'!$B$2:$B$440,2021,'Set B daily'!$C$2:$C$440,12) -> 11263 | N24: =SUM(B24:M24) -> 194203 | O24: =COUNTIFS('Set B daily'!$B$2:$B$440,2021) -> 52 | P24: =COUNTIFS('Set B daily'!$B$2:$B$440,2021,'Set B daily'!$P$2:$P$440,">0") -> 43
A25: 2022 | B25: =SUMIFS('Set B daily'!$P$2:$P$440,'Set B daily'!$B$2:$B$440,2022,'Set B daily'!$C$2:$C$440,1) -> -3893 | C25: =SUMIFS('Set B daily'!$P$2:$P$440,'Set B daily'!$B$2:$B$440,2022,'Set B daily'!$C$2:$C$440,2) -> -7941 | D25: =SUMIFS('Set B daily'!$P$2:$P$440,'Set B daily'!$B$2:$B$440,2022,'Set B daily'!$C$2:$C$440,3) -> 34536 | E25: =SUMIFS('Set B daily'!$P$2:$P$440,'Set B daily'!$B$2:$B$440,2022,'Set B daily'!$C$2:$C$440,4) -> 12959 | F25: =SUMIFS('Set B daily'!$P$2:$P$440,'Set B daily'!$B$2:$B$440,2022,'Set B daily'!$C$2:$C$440,5) -> -1834 | G25: =SUMIFS('Set B daily'!$P$2:$P$440,'Set B daily'!$B$2:$B$440,2022,'Set B daily'!$C$2:$C$440,6) -> 11427 | H25: =SUMIFS('Set B daily'!$P$2:$P$440,'Set B daily'!$B$2:$B$440,2022,'Set B daily'!$C$2:$C$440,7) -> 35619 | I25: =SUMIFS('Set B daily'!$P$2:$P$440,'Set B daily'!$B$2:$B$440,2022,'Set B daily'!$C$2:$C$440,8) -> 23245 | J25: =SUMIFS('Set B daily'!$P$2:$P$440,'Set B daily'!$B$2:$B$440,2022,'Set B daily'!$C$2:$C$440,9) -> 27712 | K25: =SUMIFS('Set B daily'!$P$2:$P$440,'Set B daily'!$B$2:$B$440,2022,'Set B daily'!$C$2:$C$440,10) -> 22626 | L25: =SUMIFS('Set B daily'!$P$2:$P$440,'Set B daily'!$B$2:$B$440,2022,'Set B daily'!$C$2:$C$440,11) -> 22512 | M25: =SUMIFS('Set B daily'!$P$2:$P$440,'Set B daily'!$B$2:$B$440,2022,'Set B daily'!$C$2:$C$440,12) -> 11983 | N25: =SUM(B25:M25) -> 188951 | O25: =COUNTIFS('Set B daily'!$B$2:$B$440,2022) -> 52 | P25: =COUNTIFS('Set B daily'!$B$2:$B$440,2022,'Set B daily'!$P$2:$P$440,">0") -> 42
A26: 2023 | B26: =SUMIFS('Set B daily'!$P$2:$P$440,'Set B daily'!$B$2:$B$440,2023,'Set B daily'!$C$2:$C$440,1) -> 8282 | C26: =SUMIFS('Set B daily'!$P$2:$P$440,'Set B daily'!$B$2:$B$440,2023,'Set B daily'!$C$2:$C$440,2) -> 14433 | D26: =SUMIFS('Set B daily'!$P$2:$P$440,'Set B daily'!$B$2:$B$440,2023,'Set B daily'!$C$2:$C$440,3) -> 1336 | E26: =SUMIFS('Set B daily'!$P$2:$P$440,'Set B daily'!$B$2:$B$440,2023,'Set B daily'!$C$2:$C$440,4) -> 8063 | F26: =SUMIFS('Set B daily'!$P$2:$P$440,'Set B daily'!$B$2:$B$440,2023,'Set B daily'!$C$2:$C$440,5) -> 1068 | G26: =SUMIFS('Set B daily'!$P$2:$P$440,'Set B daily'!$B$2:$B$440,2023,'Set B daily'!$C$2:$C$440,6) -> 8665 | H26: =SUMIFS('Set B daily'!$P$2:$P$440,'Set B daily'!$B$2:$B$440,2023,'Set B daily'!$C$2:$C$440,7) -> 15242 | I26: =SUMIFS('Set B daily'!$P$2:$P$440,'Set B daily'!$B$2:$B$440,2023,'Set B daily'!$C$2:$C$440,8) -> 11078 | J26: =SUMIFS('Set B daily'!$P$2:$P$440,'Set B daily'!$B$2:$B$440,2023,'Set B daily'!$C$2:$C$440,9) -> 11502 | K26: =SUMIFS('Set B daily'!$P$2:$P$440,'Set B daily'!$B$2:$B$440,2023,'Set B daily'!$C$2:$C$440,10) -> 10434 | L26: =SUMIFS('Set B daily'!$P$2:$P$440,'Set B daily'!$B$2:$B$440,2023,'Set B daily'!$C$2:$C$440,11) -> 18137 | M26: =SUMIFS('Set B daily'!$P$2:$P$440,'Set B daily'!$B$2:$B$440,2023,'Set B daily'!$C$2:$C$440,12) -> 16332 | N26: =SUM(B26:M26) -> 124572 | O26: =COUNTIFS('Set B daily'!$B$2:$B$440,2023) -> 52 | P26: =COUNTIFS('Set B daily'!$B$2:$B$440,2023,'Set B daily'!$P$2:$P$440,">0") -> 39
A27: 2024 | B27: =SUMIFS('Set B daily'!$P$2:$P$440,'Set B daily'!$B$2:$B$440,2024,'Set B daily'!$C$2:$C$440,1) -> 15107 | C27: =SUMIFS('Set B daily'!$P$2:$P$440,'Set B daily'!$B$2:$B$440,2024,'Set B daily'!$C$2:$C$440,2) -> 30956 | D27: =SUMIFS('Set B daily'!$P$2:$P$440,'Set B daily'!$B$2:$B$440,2024,'Set B daily'!$C$2:$C$440,3) -> -3542 | E27: =SUMIFS('Set B daily'!$P$2:$P$440,'Set B daily'!$B$2:$B$440,2024,'Set B daily'!$C$2:$C$440,4) -> -23385 | F27: =SUMIFS('Set B daily'!$P$2:$P$440,'Set B daily'!$B$2:$B$440,2024,'Set B daily'!$C$2:$C$440,5) -> 38881 | G27: =SUMIFS('Set B daily'!$P$2:$P$440,'Set B daily'!$B$2:$B$440,2024,'Set B daily'!$C$2:$C$440,6) -> 38855 | H27: =SUMIFS('Set B daily'!$P$2:$P$440,'Set B daily'!$B$2:$B$440,2024,'Set B daily'!$C$2:$C$440,7) -> 11216 | I27: =SUMIFS('Set B daily'!$P$2:$P$440,'Set B daily'!$B$2:$B$440,2024,'Set B daily'!$C$2:$C$440,8) -> 33633 | J27: =SUMIFS('Set B daily'!$P$2:$P$440,'Set B daily'!$B$2:$B$440,2024,'Set B daily'!$C$2:$C$440,9) -> 13100 | K27: =SUMIFS('Set B daily'!$P$2:$P$440,'Set B daily'!$B$2:$B$440,2024,'Set B daily'!$C$2:$C$440,10) -> 48705 | L27: =SUMIFS('Set B daily'!$P$2:$P$440,'Set B daily'!$B$2:$B$440,2024,'Set B daily'!$C$2:$C$440,11) -> 45696 | M27: =SUMIFS('Set B daily'!$P$2:$P$440,'Set B daily'!$B$2:$B$440,2024,'Set B daily'!$C$2:$C$440,12) -> 12130 | N27: =SUM(B27:M27) -> 261352 | O27: =COUNTIFS('Set B daily'!$B$2:$B$440,2024) -> 52 | P27: =COUNTIFS('Set B daily'!$B$2:$B$440,2024,'Set B daily'!$P$2:$P$440,">0") -> 39
A28: 2025 | B28: =SUMIFS('Set B daily'!$P$2:$P$440,'Set B daily'!$B$2:$B$440,2025,'Set B daily'!$C$2:$C$440,1) -> 31881 | C28: =SUMIFS('Set B daily'!$P$2:$P$440,'Set B daily'!$B$2:$B$440,2025,'Set B daily'!$C$2:$C$440,2) -> 29017 | D28: =SUMIFS('Set B daily'!$P$2:$P$440,'Set B daily'!$B$2:$B$440,2025,'Set B daily'!$C$2:$C$440,3) -> 13994 | E28: =SUMIFS('Set B daily'!$P$2:$P$440,'Set B daily'!$B$2:$B$440,2025,'Set B daily'!$C$2:$C$440,4) -> 41070 | F28: =SUMIFS('Set B daily'!$P$2:$P$440,'Set B daily'!$B$2:$B$440,2025,'Set B daily'!$C$2:$C$440,5) -> 35728 | G28: =SUMIFS('Set B daily'!$P$2:$P$440,'Set B daily'!$B$2:$B$440,2025,'Set B daily'!$C$2:$C$440,6) -> 7072 | H28: =SUMIFS('Set B daily'!$P$2:$P$440,'Set B daily'!$B$2:$B$440,2025,'Set B daily'!$C$2:$C$440,7) -> 17807 | I28: =SUMIFS('Set B daily'!$P$2:$P$440,'Set B daily'!$B$2:$B$440,2025,'Set B daily'!$C$2:$C$440,8) -> -5012 | J28: =SUMIFS('Set B daily'!$P$2:$P$440,'Set B daily'!$B$2:$B$440,2025,'Set B daily'!$C$2:$C$440,9) -> -3487 | K28: =SUMIFS('Set B daily'!$P$2:$P$440,'Set B daily'!$B$2:$B$440,2025,'Set B daily'!$C$2:$C$440,10) -> -920 | L28: =SUMIFS('Set B daily'!$P$2:$P$440,'Set B daily'!$B$2:$B$440,2025,'Set B daily'!$C$2:$C$440,11) -> 8959 | M28: =SUMIFS('Set B daily'!$P$2:$P$440,'Set B daily'!$B$2:$B$440,2025,'Set B daily'!$C$2:$C$440,12) -> 27136 | N28: =SUM(B28:M28) -> 203245 | O28: =COUNTIFS('Set B daily'!$B$2:$B$440,2025) -> 53 | P28: =COUNTIFS('Set B daily'!$B$2:$B$440,2025,'Set B daily'!$P$2:$P$440,">0") -> 37
A29: 2026 | B29: =SUMIFS('Set B daily'!$P$2:$P$440,'Set B daily'!$B$2:$B$440,2026,'Set B daily'!$C$2:$C$440,1) -> 2777 | C29: =SUMIFS('Set B daily'!$P$2:$P$440,'Set B daily'!$B$2:$B$440,2026,'Set B daily'!$C$2:$C$440,2) -> 68111 | D29: =SUMIFS('Set B daily'!$P$2:$P$440,'Set B daily'!$B$2:$B$440,2026,'Set B daily'!$C$2:$C$440,3) -> 55640 | E29: =SUMIFS('Set B daily'!$P$2:$P$440,'Set B daily'!$B$2:$B$440,2026,'Set B daily'!$C$2:$C$440,4) -> 36988 | F29: =SUMIFS('Set B daily'!$P$2:$P$440,'Set B daily'!$B$2:$B$440,2026,'Set B daily'!$C$2:$C$440,5) -> 24231 | G29: =SUMIFS('Set B daily'!$P$2:$P$440,'Set B daily'!$B$2:$B$440,2026,'Set B daily'!$C$2:$C$440,6) -> -3682 | H29: =SUMIFS('Set B daily'!$P$2:$P$440,'Set B daily'!$B$2:$B$440,2026,'Set B daily'!$C$2:$C$440,7) -> 13687 | I29: =SUMIFS('Set B daily'!$P$2:$P$440,'Set B daily'!$B$2:$B$440,2026,'Set B daily'!$C$2:$C$440,8) -> 24268 | J29: =SUMIFS('Set B daily'!$P$2:$P$440,'Set B daily'!$B$2:$B$440,2026,'Set B daily'!$C$2:$C$440,9) -> 14601 | K29: =SUMIFS('Set B daily'!$P$2:$P$440,'Set B daily'!$B$2:$B$440,2026,'Set B daily'!$C$2:$C$440,10) -> 9117 | L29: =SUMIFS('Set B daily'!$P$2:$P$440,'Set B daily'!$B$2:$B$440,2026,'Set B daily'!$C$2:$C$440,11) -> 0 | M29: =SUMIFS('Set B daily'!$P$2:$P$440,'Set B daily'!$B$2:$B$440,2026,'Set B daily'!$C$2:$C$440,12) -> 0 | N29: =SUM(B29:M29) -> 245738 | O29: =COUNTIFS('Set B daily'!$B$2:$B$440,2026) -> 42 | P29: =COUNTIFS('Set B daily'!$B$2:$B$440,2026,'Set B daily'!$P$2:$P$440,">0") -> 30
A30: Total | B30: =SUM(B19:B29) -> 82513 | C30: =SUM(C19:C29) -> 170069 | D30: =SUM(D19:D29) -> 153871 | E30: =SUM(E19:E29) -> 92588 | F30: =SUM(F19:F29) -> 169866 | G30: =SUM(G19:G29) -> 56930 | H30: =SUM(H19:H29) -> 116111 | I30: =SUM(I19:I29) -> 136799 | ... P30: =SUM(P19:P29) -> 321

Sheet Yearly
A1: Year | B1: Set A ₹ (9:22+9:35+10:05) | C1: Set A expiry days | D1: Set A win % | E1: Set A worst day ₹ | F1: Set B ₹ (9:45+10:05+10:35) | G1: Set B expiry days | H1: Set B win % | I1: Set B worst day ₹
A2: 2016 | B2: =SUMIFS('Set A daily'!$P$2:$P$440,'Set A daily'!$B$2:$B$440,2016) -> 4314 | C2: =COUNTIFS('Set A daily'!$B$2:$B$440,2016) -> 12 | D2: =IFERROR(COUNTIFS('Set A daily'!$B$2:$B$440,2016,'Set A daily'!$P$2:$P$440,">0")/C2,0) -> 0.33333333 | E2: =_xlfn.MINIFS('Set A daily'!$P$2:$P$440,'Set A daily'!$B$2:$B$440,2016) -> -2475 | F2: =SUMIFS('Set B daily'!$P$2:$P$440,'Set B daily'!$B$2:$B$440,2016) -> 8218 | G2: =COUNTIFS('Set B daily'!$B$2:$B$440,2016) -> 12 | H2: =IFERROR(COUNTIFS('Set B daily'!$B$2:$B$440,2016,'Set B daily'!$P$2:$P$440,">0")/G2,0) -> 0.66666667 | I2: =_xlfn.MINIFS('Set B daily'!$P$2:$P$440,'Set B daily'!$B$2:$B$440,2016) -> -2488
A3: 2017 | B3: =SUMIFS('Set A daily'!$P$2:$P$440,'Set A daily'!$B$2:$B$440,2017) -> 11490 | C3: =COUNTIFS('Set A daily'!$B$2:$B$440,2017) -> 12 | D3: =IFERROR(COUNTIFS('Set A daily'!$B$2:$B$440,2017,'Set A daily'!$P$2:$P$440,">0")/C3,0) -> 0.66666667 | E3: =_xlfn.MINIFS('Set A daily'!$P$2:$P$440,'Set A daily'!$B$2:$B$440,2017) -> -4025 | F3: =SUMIFS('Set B daily'!$P$2:$P$440,'Set B daily'!$B$2:$B$440,2017) -> -2918 | G3: =COUNTIFS('Set B daily'!$B$2:$B$440,2017) -> 12 | H3: =IFERROR(COUNTIFS('Set B daily'!$B$2:$B$440,2017,'Set B daily'!$P$2:$P$440,">0")/G3,0) -> 0.33333333 | I3: =_xlfn.MINIFS('Set B daily'!$P$2:$P$440,'Set B daily'!$B$2:$B$440,2017) -> -3819
A4: 2018 | B4: =SUMIFS('Set A daily'!$P$2:$P$440,'Set A daily'!$B$2:$B$440,2018) -> 14995 | C4: =COUNTIFS('Set A daily'!$B$2:$B$440,2018) -> 12 | D4: =IFERROR(COUNTIFS('Set A daily'!$B$2:$B$440,2018,'Set A daily'!$P$2:$P$440,">0")/C4,0) -> 0.58333333 | E4: =_xlfn.MINIFS('Set A daily'!$P$2:$P$440,'Set A daily'!$B$2:$B$440,2018) -> -3288 | F4: =SUMIFS('Set B daily'!$P$2:$P$440,'Set B daily'!$B$2:$B$440,2018) -> 10196 | G4: =COUNTIFS('Set B daily'!$B$2:$B$440,2018) -> 12 | H4: =IFERROR(COUNTIFS('Set B daily'!$B$2:$B$440,2018,'Set B daily'!$P$2:$P$440,">0")/G4,0) -> 0.75 | I4: =_xlfn.MINIFS('Set B daily'!$P$2:$P$440,'Set B daily'!$B$2:$B$440,2018) -> -3197
A5: 2019 | B5: =SUMIFS('Set A daily'!$P$2:$P$440,'Set A daily'!$B$2:$B$440,2019) -> 73907 | C5: =COUNTIFS('Set A daily'!$B$2:$B$440,2019) -> 47 | D5: =IFERROR(COUNTIFS('Set A daily'!$B$2:$B$440,2019,'Set A daily'!$P$2:$P$440,">0")/C5,0) -> 0.70212766 | E5: =_xlfn.MINIFS('Set A daily'!$P$2:$P$440,'Set A daily'!$B$2:$B$440,2019) -> -4768 | F5: =SUMIFS('Set B daily'!$P$2:$P$440,'Set B daily'!$B$2:$B$440,2019) -> 75846 | G5: =COUNTIFS('Set B daily'!$B$2:$B$440,2019) -> 47 | H5: =IFERROR(COUNTIFS('Set B daily'!$B$2:$B$440,2019,'Set B daily'!$P$2:$P$440,">0")/G5,0) -> 0.72340426 | I5: =_xlfn.MINIFS('Set B daily'!$P$2:$P$440,'Set B daily'!$B$2:$B$440,2019) -> -4655
A6: 2020 | B6: =SUMIFS('Set A daily'!$P$2:$P$440,'Set A daily'!$B$2:$B$440,2020) -> 141739 | C6: =COUNTIFS('Set A daily'!$B$2:$B$440,2020) -> 53 | D6: =IFERROR(COUNTIFS('Set A daily'!$B$2:$B$440,2020,'Set A daily'!$P$2:$P$440,">0")/C6,0) -> 0.69811321 | E6: =_xlfn.MINIFS('Set A daily'!$P$2:$P$440,'Set A daily'!$B$2:$B$440,2020) -> -4740 | F6: =SUMIFS('Set B daily'!$P$2:$P$440,'Set B daily'!$B$2:$B$440,2020) -> 145131 | G6: =COUNTIFS('Set B daily'!$B$2:$B$440,2020) -> 53 | H6: =IFERROR(COUNTIFS('Set B daily'!$B$2:$B$440,2020,'Set B daily'!$P$2:$P$440,">0")/G6,0) -> 0.67924528 | I6: =_xlfn.MINIFS('Set B daily'!$P$2:$P$440,'Set B daily'!$B$2:$B$440,2020) -> -11766
A7: 2021 | B7: =SUMIFS('Set A daily'!$P$2:$P$440,'Set A daily'!$B$2:$B$440,2021) -> 167333 | C7: =COUNTIFS('Set A daily'!$B$2:$B$440,2021) -> 52 | D7: =IFERROR(COUNTIFS('Set A daily'!$B$2:$B$440,2021,'Set A daily'!$P$2:$P$440,">0")/C7,0) -> 0.78846154 | E7: =_xlfn.MINIFS('Set A daily'!$P$2:$P$440,'Set A daily'!$B$2:$B$440,2021) -> -7127 | F7: =SUMIFS('Set B daily'!$P$2:$P$440,'Set B daily'!$B$2:$B$440,2021) -> 194203 | G7: =COUNTIFS('Set B daily'!$B$2:$B$440,2021) -> 52 | H7: =IFERROR(COUNTIFS('Set B daily'!$B$2:$B$440,2021,'Set B daily'!$P$2:$P$440,">0")/G7,0) -> 0.82692308 | I7: =_xlfn.MINIFS('Set B daily'!$P$2:$P$440,'Set B daily'!$B$2:$B$440,2021) -> -7220
A8: 2022 | B8: =SUMIFS('Set A daily'!$P$2:$P$440,'Set A daily'!$B$2:$B$440,2022) -> 196059 | C8: =COUNTIFS('Set A daily'!$B$2:$B$440,2022) -> 52 | D8: =IFERROR(COUNTIFS('Set A daily'!$B$2:$B$440,2022,'Set A daily'!$P$2:$P$440,">0")/C8,0) -> 0.78846154 | E8: =_xlfn.MINIFS('Set A daily'!$P$2:$P$440,'Set A daily'!$B$2:$B$440,2022) -> -10173 | F8: =SUMIFS('Set B daily'!$P$2:$P$440,'Set B daily'!$B$2:$B$440,2022) -> 188951 | G8: =COUNTIFS('Set B daily'!$B$2:$B$440,2022) -> 52 | H8: =IFERROR(COUNTIFS('Set B daily'!$B$2:$B$440,2022,'Set B daily'!$P$2:$P$440,">0")/G8,0) -> 0.80769231 | I8: =_xlfn.MINIFS('Set B daily'!$P$2:$P$440,'Set B daily'!$B$2:$B$440,2022) -> -13066
A9: 2023 | B9: =SUMIFS('Set A daily'!$P$2:$P$440,'Set A daily'!$B$2:$B$440,2023) -> 61354 | C9: =COUNTIFS('Set A daily'!$B$2:$B$440,2023) -> 52 | D9: =IFERROR(COUNTIFS('Set A daily'!$B$2:$B$440,2023,'Set A daily'!$P$2:$P$440,">0")/C9,0) -> 0.65384615 | E9: =_xlfn.MINIFS('Set A daily'!$P$2:$P$440,'Set A daily'!$B$2:$B$440,2023) -> -6809 | F9: =SUMIFS('Set B daily'!$P$2:$P$440,'Set B daily'!$B$2:$B$440,2023) -> 124572 | G9: =COUNTIFS('Set B daily'!$B$2:$B$440,2023) -> 52 | H9: =IFERROR(COUNTIFS('Set B daily'!$B$2:$B$440,2023,'Set B daily'!$P$2:$P$440,">0")/G9,0) -> 0.75 | I9: =_xlfn.MINIFS('Set B daily'!$P$2:$P$440,'Set B daily'!$B$2:$B$440,2023) -> -5705
A10: 2024 | B10: =SUMIFS('Set A daily'!$P$2:$P$440,'Set A daily'!$B$2:$B$440,2024) -> 248925 | C10: =COUNTIFS('Set A daily'!$B$2:$B$440,2024) -> 52 | D10: =IFERROR(COUNTIFS('Set A daily'!$B$2:$B$440,2024,'Set A daily'!$P$2:$P$440,">0")/C10,0) -> 0.73076923 | E10: =_xlfn.MINIFS('Set A daily'!$P$2:$P$440,'Set A daily'!$B$2:$B$440,2024) -> -14841 | F10: =SUMIFS('Set B daily'!$P$2:$P$440,'Set B daily'!$B$2:$B$440,2024) -> 261352 | G10: =COUNTIFS('Set B daily'!$B$2:$B$440,2024) -> 52 | H10: =IFERROR(COUNTIFS('Set B daily'!$B$2:$B$440,2024,'Set B daily'!$P$2:$P$440,">0")/G10,0) -> 0.75 | I10: =_xlfn.MINIFS('Set B daily'!$P$2:$P$440,'Set B daily'!$B$2:$B$440,2024) -> -14240
A11: 2025 | B11: =SUMIFS('Set A daily'!$P$2:$P$440,'Set A daily'!$B$2:$B$440,2025) -> 200035 | C11: =COUNTIFS('Set A daily'!$B$2:$B$440,2025) -> 53 | D11: =IFERROR(COUNTIFS('Set A daily'!$B$2:$B$440,2025,'Set A daily'!$P$2:$P$440,">0")/C11,0) -> 0.67924528 | E11: =_xlfn.MINIFS('Set A daily'!$P$2:$P$440,'Set A daily'!$B$2:$B$440,2025) -> -8131 | F11: =SUMIFS('Set B daily'!$P$2:$P$440,'Set B daily'!$B$2:$B$440,2025) -> 203245 | G11: =COUNTIFS('Set B daily'!$B$2:$B$440,2025) -> 53 | H11: =IFERROR(COUNTIFS('Set B daily'!$B$2:$B$440,2025,'Set B daily'!$P$2:$P$440,">0")/G11,0) -> 0.69811321 | I11: =_xlfn.MINIFS('Set B daily'!$P$2:$P$440,'Set B daily'!$B$2:$B$440,2025) -> -8550
A12: 2026 | B12: =SUMIFS('Set A daily'!$P$2:$P$440,'Set A daily'!$B$2:$B$440,2026) -> 207785 | C12: =COUNTIFS('Set A daily'!$B$2:$B$440,2026) -> 42 | D12: =IFERROR(COUNTIFS('Set A daily'!$B$2:$B$440,2026,'Set A daily'!$P$2:$P$440,">0")/C12,0) -> 0.73809524 | E12: =_xlfn.MINIFS('Set A daily'!$P$2:$P$440,'Set A daily'!$B$2:$B$440,2026) -> -7319 | F12: =SUMIFS('Set B daily'!$P$2:$P$440,'Set B daily'!$B$2:$B$440,2026) -> 245738 | G12: =COUNTIFS('Set B daily'!$B$2:$B$440,2026) -> 42 | H12: =IFERROR(COUNTIFS('Set B daily'!$B$2:$B$440,2026,'Set B daily'!$P$2:$P$440,">0")/G12,0) -> 0.71428571 | I12: =_xlfn.MINIFS('Set B daily'!$P$2:$P$440,'Set B daily'!$B$2:$B$440,2026) -> -11205
A13: Total | B13: =SUM(B2:B12) -> 1327936 | C13: =SUM(C2:C12) -> 439 | D13: =SUMPRODUCT(D2:D12,C2:C12)/C13 -> 0.70615034 | E13: =MIN(E2:E12) -> -14841 | F13: =SUM(F2:F12) -> 1454534 | G13: =SUM(G2:G12) -> 439 | H13: =SUMPRODUCT(H2:H12,G2:G12)/G13 -> 0.73120729 | I13: =MIN(I2:I12) -> -14240
